{
  "project_info": {
    "project_number": "10003241290",
    "project_id": "the-blood-alliance-2691f",
    "storage_bucket": "the-blood-alliance-2691f.appspot.com"
  },
  "client": [
    {
      "client_info": {
        "mobilesdk_app_id": "1:10003241290:android:fbeba8c71ab91bc8f309b3",
        "android_client_info": {
          "package_name": "com.example.practice"
        }
      },
      "oauth_client": [
        {
          "client_id": "10003241290-4mgveadq8tsjdi0op5drfhh0sffk847g.apps.googleusercontent.com",
          "client_type": 3
        }
      ],
      "api_key": [
        {
          "current_key": "AIzaSyCznnJLvqhWIqPTKwKx_EO0wplDbX1vvvI"
        }
      ],
      "services": {
        "appinvite_service": {
          "other_platform_oauth_client": [
            {
              "client_id": "10003241290-4mgveadq8tsjdi0op5drfhh0sffk847g.apps.googleusercontent.com",
              "client_type": 3
            }
          ]
        }
      }
    }
  ],
  "configuration_version": "1"
}